{
  "markerSets": [
    {
      "id": "markers",
      "label": "Markers",
      "toggleable": true,
      "defaultHide": false,
      "marker": [
        {
          "id": "makotohouse",
          "type": "poi",
          "map": "world",
          "position": {
            "x": 261.0,
            "y": 65.0,
            "z": 1189.0
          },
          "minDistance": 0.0,
          "maxDistance": 100000.0,
          "label": "まことさんのおうち",
          "newTab": true,
          "icon": "assets/poi.svg",
          "anchor": {
            "x": 25,
            "y": 45
          }
        },
        {
          "id": "endportal",
          "type": "poi",
          "map": "world",
          "position": {
            "x": 1362.0,
            "y": 64.0,
            "z": -493.0
          },
          "minDistance": 0.0,
          "maxDistance": 100000.0,
          "label": "エンドポータルのある要塞",
          "newTab": true,
          "icon": "assets/poi.svg",
          "anchor": {
            "x": 25,
            "y": 45
          }
        },
        {
          "id": "storage",
          "type": "poi",
          "map": "world",
          "position": {
            "x": 22.0,
            "y": 66.0,
            "z": 60.0
          },
          "minDistance": 0.0,
          "maxDistance": 100000.0,
          "label": "倉庫",
          "newTab": true,
          "icon": "assets/poi.svg",
          "anchor": {
            "x": 25,
            "y": 45
          }
        },
        {
          "id": "trap",
          "type": "poi",
          "map": "world",
          "position": {
            "x": -423.0,
            "y": 241.0,
            "z": -121.0
          },
          "minDistance": 0.0,
          "maxDistance": 100000.0,
          "label": "天空トラップタワー",
          "newTab": true,
          "icon": "assets/poi.svg",
          "anchor": {
            "x": 25,
            "y": 45
          }
        },
        {
          "id": "typomhome",
          "type": "poi",
          "map": "world",
          "position": {
            "x": -10.0,
            "y": 65.0,
            "z": 1043.0
          },
          "minDistance": 0.0,
          "maxDistance": 100000.0,
          "label": "つよポンの初期拠点",
          "newTab": true,
          "icon": "assets/poi.svg",
          "anchor": {
            "x": 25,
            "y": 45
          }
        },
        {
          "id": "endWorldBorder",
          "type": "line",
          "map": "world_the_end",
          "position": {
            "x": -3000,
            "y": 64,
            "z": -3000
          },
          "label": "ワールドボーダー",
          "detail": "これより先には行けない",
          "line": [
            {
              "x": -5000,
              "y": 64,
              "z": -5000
            },
            {
              "x": 5000,
              "y": 64,
              "z": -5000
            },
            {
              "x": 5000,
              "y": 64,
              "z": 5000
            },
            {
              "x": -5000,
              "y": 64,
              "z": 5000
            },
            {
              "x": -5000,
              "y": 64,
              "z": -5000
            }
          ],
          "depthTest": true,
          "lineWidth": 5,
          "lineColor": {
            "r": 255,
            "g": 64,
            "b": 64,
            "a": 1
          },
          "minDistance": 0.0,
          "maxDistance": 100000.0
        },
        {
          "id": "worldWorldBorder",
          "type": "line",
          "map": "world",
          "position": {
            "x": -3000,
            "y": 64,
            "z": -3000
          },
          "label": "ワールドボーダー",
          "detail": "これより先には行けない",
          "line": [
            {
              "x": -3000,
              "y": 64,
              "z": -3000
            },
            {
              "x": 3000,
              "y": 64,
              "z": -3000
            },
            {
              "x": 3000,
              "y": 64,
              "z": 3000
            },
            {
              "x": -3000,
              "y": 64,
              "z": 3000
            },
            {
              "x": -3000,
              "y": 64,
              "z": -3000
            }
          ],
          "depthTest": true,
          "lineWidth": 5,
          "lineColor": {
            "r": 255,
            "g": 64,
            "b": 64,
            "a": 1
          },
          "minDistance": 0.0,
          "maxDistance": 100000.0
        }
      ]
    }
  ]
}
